Metadata-Version: 2.1
Name: layerx-sdk-beta
Version: 1.0.16b9
Summary: LayerX Python SDK
Author: LayerNext
Author-email: <support@layernext.ai>
Keywords: python,datalake,datasetsync,ai,annotation,layerx,layernext,machine learning
Classifier: Development Status :: 1 - Planning
Classifier: Intended Audience :: Developers
Classifier: Programming Language :: Python :: 3
Classifier: Operating System :: Unix
Classifier: Operating System :: MacOS :: MacOS X
Classifier: Operating System :: Microsoft :: Windows
Requires-Dist: requests
Requires-Dist: uuid
Requires-Dist: python-dotenv
Requires-Dist: azure-storage-blob
